bluenetwork/__init__.py
bluenetwork/networkservice.py
bluenetwork-0.1.dist-info/LICENSE
bluenetwork-0.1.dist-info/METADATA
bluenetwork-0.1.dist-info/WHEEL
bluenetwork-0.1.dist-info/top_level.txt
bluenetwork-0.1.dist-info/RECORD
